{"ApprovalTime": "2017-03-21T05:45:16Z", "AutoApprovalTime": "2017-03-21T05:44:26Z", "AssignmentId": "34YB12FSQYO45MH3MUWG0A046SKGM0", "WorkerId": "anon18", "answers": {"data": {"good_ep": [false, false, true, true, true, true, true, true, true, true, true, true, true, true, true, true, true, true, true, true, true, true, true, true, true, true, true, true, true, true, true, true, true, true, true, true, true, true, true, true, true, true, true, true, true, true, true, true, true, true], "window_width": [1215, 1215, 1215, 1215, 1215, 1215, 1215, 1215, 1215, 1215, 1215, 1215, 1215, 1215, 1215, 1215, 1215, 1215, 1215, 1215, 1215, 1215, 1215, 1215, 1215, 1215, 1215, 1215, 1215, 1215, 1215, 1215, 1215, 1215, 1215, 1215, 1215, 1215, 1215, 1215, 1215, 1215, 1215, 1215, 1215, 1215, 1215, 1215, 1215, 1215], "expt_gen": ["no"], "education": ["someCollege"], "ratings": [["2", "3", "6"], ["3", "4", "6", "7"], ["1", "2"], ["1", "2"], ["1"], ["1", "2"], ["1", "2"], ["6", "7"], ["1", "2"], ["1", "2"], ["7"], ["7"], ["1"], ["7"], ["1"], ["1"], ["1"], ["1", "2"], ["7"], ["7"], ["7"], ["6", "7"], ["6", "7"], ["1", "2"], ["1"], ["7"], ["7"], ["7"], ["1"], ["1", "2"], ["7"], ["7"], ["6", "7"], ["6", "7"], ["1", "2"], ["6", "7"], ["1"], ["7"], ["1"], ["1"], ["7"], ["1"], ["7"], ["6", "7"], ["6", "7"], ["1"], ["1"], ["1"], ["7"], ["7"]], "non_consecutive": [true, true, false, false, false, false, false, false, false, false, false, false, false, false, false, false, false, false, false, false, false, false, false, false, false, false, false, false, false, false, false, false, false, false, false, false, false, false, false, false, false, false, false, false, false, false, false, false, false, false], "elapsed_first_click_ms": [4913, 4326, 2668, 1483, 1846, 1163, 1228, 1438, 1405, 611, 1798, 1469, 658, 1146, 1048, 1799, 1590, 1007, 1268, 1220, 1075, 863, 1040, 789, 1217, 1191, 1327, 894, 1185, 649, 1115, 912, 832, 1542, 1083, 569, 734, 1237, 349, 875, 1452, 846, 1015, 501, 507, 1011, 1035, 953, 1175, 960], "adj": ["pretty", "ugly", "big", "small", "big", "big", "small", "big", "small", "big", "big", "small", "big", "big", "small", "small", "small", "big", "small", "big", "big", "big", "big", "big", "small", "small", "small", "small", "small", "big", "small", "small", "big", "big", "big", "big", "big", "small", "big", "small", "small", "big", "small", "big", "big", "small", "small", "small", "small", "small"], "num_errors": [], "dpi_width": [0, 0, 0, 0, 0, 0, 0, 0, 0, 0, 0, 0, 0, 0, 0, 0, 0, 0, 0, 0, 0, 0, 0, 0, 0, 0, 0, 0, 0, 0, 0, 0, 0, 0, 0, 0, 0, 0, 0, 0, 0, 0, 0, 0, 0, 0, 0, 0, 0, 0], "window_height": [950, 950, 950, 950, 950, 950, 950, 950, 950, 950, 950, 950, 950, 950, 950, 950, 950, 950, 950, 950, 950, 950, 950, 950, 950, 950, 950, 950, 950, 950, 950, 950, 950, 950, 950, 950, 950, 950, 950, 950, 950, 950, 950, 950, 950, 950, 950, 950, 950, 950], "screen_size": ["22"], "none_checked": [false, false, false, false, false, false, false, false, false, false, false, false, false, false, false, false, false, false, false, false, false, false, false, false, false, false, false, false, false, false, false, false, false, false, false, false, false, false, false, false, false, false, false, false, false, false, false, false, false, false], "elapsed_ms": [14880, 12536, 5035, 3347, 6826, 4057, 2920, 4999, 2409, 1764, 2718, 2496, 2910, 2373, 1922, 3079, 2320, 2964, 1932, 2407, 2335, 2361, 4360, 1936, 1891, 2045, 2223, 1588, 2168, 1722, 1889, 1635, 1949, 2619, 2276, 1669, 3071, 3297, 1244, 1565, 2279, 2545, 1832, 1447, 1446, 1748, 1835, 1623, 1968, 1770], "verb": ["find", "find", "find", "find", "find", "find", "find", "find", "find", "find", "find", "find", "find", "find", "find", "find", "find", "find", "find", "find", "find", "find", "find", "find", "find", "find", "find", "find", "find", "find", "find", "find", "find", "find", "find", "find", "find", "find", "find", "find", "find", "find", "find", "find", "find", "find", "find", "find", "find", "find"], "is_endpoint": [false, true, true, true, true, true, true, true, true, true, true, true, true, true, true, true, true, true, true, true, true, true, true, true, true, true, true, true, true, true, true, true, true, true, true, true, true, true, true, true, true, true, true, true, true, true, true, true, true, true], "lang": ["English"], "endpoint": ["na", 7, 1, 1, 1, 1, 1, 7, 1, 1, 7, 7, 1, 7, 1, 1, 1, 1, 7, 7, 7, 7, 7, 1, 1, 7, 7, 7, 1, 1, 7, 7, 7, 7, 1, 7, 1, 7, 1, 1, 7, 1, 7, 7, 7, 1, 1, 1, 7, 7], "noun": ["pretty", "car", "hippo", "balloon", "house", "mouse", "gnome", "umbrella", "elephant", "monkey", "cake", "chick", "gnome", "elephant", "umbrella", "hippo", "plane", "cake", "umbrella", "balloon", "house", "chick", "monkey", "chick", "cake", "mouse", "plane", "house", "monkey", "plane", "hippo", "monkey", "gnome", "baby", "elephant", "plane", "balloon", "gnome", "umbrella", "mouse", "elephant", "baby", "balloon", "hippo", "mouse", "baby", "house", "chick", "cake", "baby"], "gender": ["male"], "age": ["20-29"], "dpi_height": [0, 0, 0, 0, 0, 0, 0, 0, 0, 0, 0, 0, 0, 0, 0, 0, 0, 0, 0, 0, 0, 0, 0, 0, 0, 0, 0, 0, 0, 0, 0, 0, 0, 0, 0, 0, 0, 0, 0, 0, 0, 0, 0, 0, 0, 0, 0, 0, 0, 0], "expt_aim": ["Comparing different peoples perceptions of the words big and small. "], "prototype_status": ["na", "na", "big", "neither", "big", "small", "small", "neither", "big", "neither", "neither", "small", "small", "big", "neither", "big", "big", "neither", "neither", "neither", "big", "small", "neither", "small", "neither", "small", "big", "big", "neither", "big", "big", "neither", "small", "small", "big", "big", "neither", "small", "neither", "small", "big", "small", "neither", "big", "small", "small", "big", "small", "neither", "small"], "race": ["white"], "user_agent": ["Mozilla/5.0 (Windows NT 6.1) AppleWebKit/537.36 (KHTML, like Gecko) Chrome/56.0.2924.87 Safari/537.36"], "num_checked": [3, 4, 2, 2, 1, 2, 2, 2, 2, 2, 1, 1, 1, 1, 1, 1, 1, 2, 1, 1, 1, 2, 2, 2, 1, 1, 1, 1, 1, 2, 1, 1, 2, 2, 2, 2, 1, 1, 1, 1, 1, 1, 1, 2, 2, 1, 1, 1, 1, 1], "dir": ["asc", "desc", "desc", "asc", "desc", "desc", "asc", "asc", "asc", "desc", "asc", "desc", "desc", "asc", "asc", "asc", "asc", "desc", "desc", "asc", "asc", "asc", "asc", "desc", "asc", "desc", "desc", "desc", "asc", "desc", "desc", "desc", "asc", "asc", "desc", "asc", "desc", "desc", "desc", "asc", "desc", "desc", "desc", "asc", "asc", "asc", "asc", "asc", "desc", "desc"]}}, "AcceptTime": "2017-03-21T05:34:12Z", "HITId": "3YLPJ8OXX8DW0YPUFXRNDINB9R1X4P", "Assignment": "", "AssignmentStatus": "Approved", "SubmitTime": "2017-03-21T05:39:26Z"}