{"ApprovalTime": "2018-06-21T02:31:46Z", "AutoApprovalTime": "2018-06-21T02:31:05Z", "AssignmentId": "3A4TN5196KHCMLA7883TZNB73YFCHF", "WorkerId": "anon40", "answers": {"data": {"good_ep": [false, false, true, true, true, true, true, true, true, true, true, true, true, true, true, true, true, true, true, true, true, true, true, true, true, true, true, true, true, true, true, true, true, true, true, true, true, true, true, true, true, true, true, true, true, true, true, true, true, true], "window_width": [1836, 1853, 1853, 1853, 1853, 1853, 1853, 1853, 1853, 1853, 1853, 1853, 1853, 1853, 1853, 1853, 1853, 1853, 1853, 1853, 1853, 1853, 1853, 1853, 1853, 1853, 1853, 1853, 1853, 1853, 1853, 1853, 1853, 1853, 1853, 1853, 1853, 1853, 1853, 1853, 1853, 1853, 1853, 1853, 1853, 1853, 1853, 1853, 1853, 1853], "expt_gen": ["None"], "education": ["4year"], "ratings": [["3", "5"], ["1", "3", "7"], ["6", "7"], ["5", "6", "7"], ["1", "2"], ["3", "4", "5", "6", "7"], ["1", "2", "3"], ["4", "5", "6", "7"], ["5", "6", "7"], ["1", "2", "3", "4", "5"], ["1", "2"], ["6", "7"], ["6", "7"], ["4", "5", "6", "7"], ["1", "2"], ["3", "4", "5", "6", "7"], ["1", "2", "3"], ["1", "2"], ["1", "2"], ["1"], ["4", "5", "6", "7"], ["1", "2", "3"], ["1", "2", "3", "4", "5"], ["1", "2", "3", "4"], ["1", "2"], ["6", "7"], ["1", "2", "3", "4", "5"], ["6", "7"], ["3", "4", "5", "6", "7"], ["1", "2", "3"], ["6", "7"], ["7"], ["1", "2"], ["3", "4", "5", "6", "7"], ["4", "5", "6", "7"], ["1", "2", "3", "4", "5"], ["1", "2", "3"], ["6", "7"], ["5", "6", "7"], ["1", "2", "3", "4"], ["5", "6", "7"], ["1", "2", "3", "4", "5"], ["3", "4", "5", "6", "7"], ["3", "4", "5", "6", "7"], ["1", "2", "3", "4", "5"], ["1", "2", "3", "4"], ["1", "2", "3"], ["1", "2", "3"], ["3", "4", "5", "6", "7"], ["5", "6", "7"]], "non_consecutive": [true, true, false, false, false, false, false, false, false, false, false, false, false, false, false, false, false, false, false, false, false, false, false, false, false, false, false, false, false, false, false, false, false, false, false, false, false, false, false, false, false, false, false, false, false, false, false, false, false, false], "elapsed_first_click_ms": [3625, 2132, 1121, 1126, 833, 1230, 1297, 1394, 1448, 1111, 963, 811, 600, 784, 842, 1167, 702, 3922, 1090, 596, 1137, 1708, 1547, 1189, 1235, 998, 1403, 1025, 240, 733, 294, 789, 224, 1084, 1068, 1039, 1145, 968, 1305, 469, 1048, 361, 1521, 1029, 500, 1010, 2007, 1069, 882, 1074], "adj": ["pretty", "ugly", "big", "big", "big", "small", "big", "small", "small", "small", "big", "big", "big", "small", "big", "small", "small", "big", "small", "big", "big", "small", "small", "big", "big", "big", "small", "big", "big", "big", "big", "big", "big", "small", "big", "small", "small", "big", "small", "big", "small", "small", "small", "small", "small", "small", "big", "small", "small", "small"], "num_errors": [], "dpi_width": [0, 0, 0, 0, 0, 0, 0, 0, 0, 0, 0, 0, 0, 0, 0, 0, 0, 0, 0, 0, 0, 0, 0, 0, 0, 0, 0, 0, 0, 0, 0, 0, 0, 0, 0, 0, 0, 0, 0, 0, 0, 0, 0, 0, 0, 0, 0, 0, 0, 0], "window_height": [947, 947, 947, 947, 947, 947, 947, 947, 947, 947, 947, 947, 947, 947, 947, 947, 947, 947, 947, 947, 947, 947, 947, 947, 947, 947, 947, 947, 947, 947, 947, 947, 947, 947, 947, 947, 947, 947, 947, 947, 947, 947, 947, 947, 947, 947, 947, 947, 947, 947], "screen_size": ["22"], "none_checked": [false, false, false, false, false, false, false, false, false, false, false, false, false, false, false, false, false, false, false, false, false, false, false, false, false, false, false, false, false, false, false, false, false, false, false, false, false, false, false, false, false, false, false, false, false, false, false, false, false, false], "elapsed_ms": [7200, 9939, 4133, 4037, 2515, 5259, 4243, 4310, 7231, 7319, 2872, 3422, 2498, 4555, 2553, 4884, 3074, 5098, 2791, 2207, 4376, 3782, 5309, 5689, 2768, 2973, 4957, 2335, 3949, 2921, 1893, 1458, 2830, 5319, 4563, 5353, 4340, 2173, 3502, 3331, 3167, 3817, 5908, 4432, 4480, 4244, 4068, 4015, 4790, 4480], "verb": ["are", "are", "are", "are", "are", "are", "are", "are", "are", "are", "are", "are", "are", "are", "are", "are", "are", "are", "are", "are", "are", "are", "are", "are", "are", "are", "are", "are", "are", "are", "are", "are", "are", "are", "are", "are", "are", "are", "are", "are", "are", "are", "are", "are", "are", "are", "are", "are", "are", "are"], "is_endpoint": [false, true, true, true, true, true, true, true, true, true, true, true, true, true, true, true, true, true, true, true, true, true, true, true, true, true, true, true, true, true, true, true, true, true, true, true, true, true, true, true, true, true, true, true, true, true, true, true, true, true], "lang": ["English"], "endpoint": ["na", 1, 7, 7, 1, 7, 1, 7, 7, 1, 1, 7, 7, 7, 1, 7, 1, 1, 1, 1, 7, 1, 1, 1, 1, 7, 1, 7, 7, 1, 7, 7, 1, 7, 7, 1, 1, 7, 7, 1, 7, 1, 7, 7, 1, 1, 1, 1, 7, 7], "noun": ["pretty", "car", "hippo", "balloon", "monkey", "house", "baby", "gnome", "baby", "elephant", "umbrella", "bunny", "house", "bunny", "plane", "elephant", "gnome", "elephant", "duckling", "cake", "baby", "bunny", "monkey", "balloon", "house", "elephant", "plane", "monkey", "duckling", "bunny", "umbrella", "cake", "hippo", "cake", "gnome", "hippo", "baby", "plane", "balloon", "duckling", "umbrella", "house", "monkey", "hippo", "cake", "umbrella", "gnome", "balloon", "plane", "duckling"], "gender": ["male"], "age": ["30-39"], "dpi_height": [0, 0, 0, 0, 0, 0, 0, 0, 0, 0, 0, 0, 0, 0, 0, 0, 0, 0, 0, 0, 0, 0, 0, 0, 0, 0, 0, 0, 0, 0, 0, 0, 0, 0, 0, 0, 0, 0, 0, 0, 0, 0, 0, 0, 0, 0, 0, 0, 0, 0], "expt_aim": ["No clue"], "prototype_status": ["na", "na", "big", "neither", "neither", "big", "small", "small", "small", "big", "neither", "small", "big", "small", "big", "big", "small", "big", "small", "neither", "small", "small", "neither", "neither", "big", "big", "big", "neither", "small", "small", "neither", "neither", "big", "neither", "small", "big", "small", "big", "neither", "small", "neither", "big", "neither", "big", "neither", "neither", "small", "neither", "big", "small"], "race": ["white"], "user_agent": ["Mozilla/5.0 (Windows NT 10.0; Win64; x64) AppleWebKit/537.36 (KHTML, like Gecko) Chrome/67.0.3396.87 Safari/537.36"], "num_checked": [2, 3, 2, 3, 2, 5, 3, 4, 3, 5, 2, 2, 2, 4, 2, 5, 3, 2, 2, 1, 4, 3, 5, 4, 2, 2, 5, 2, 5, 3, 2, 1, 2, 5, 4, 5, 3, 2, 3, 4, 3, 5, 5, 5, 5, 4, 3, 3, 5, 3], "dir": ["asc", "desc", "asc", "asc", "desc", "desc", "desc", "desc", "desc", "asc", "desc", "asc", "asc", "desc", "desc", "desc", "asc", "desc", "asc", "desc", "asc", "asc", "asc", "desc", "desc", "asc", "asc", "asc", "asc", "desc", "asc", "asc", "desc", "desc", "asc", "asc", "asc", "asc", "desc", "desc", "desc", "asc", "desc", "desc", "asc", "asc", "desc", "asc", "desc", "desc"]}}, "AcceptTime": "2018-06-21T01:28:38Z", "HITId": "366FYU4PTFOGZPXZKI6JDJWEJ2WKER", "Assignment": "", "AssignmentStatus": "Approved", "SubmitTime": "2018-06-21T02:26:05Z"}