{"ApprovalTime": "2017-08-04T18:15:22Z", "AutoApprovalTime": "2017-08-04T18:15:17Z", "AssignmentId": "3LOTDFNYA7Y1MNP6U9FU8W6WJEWFW1", "WorkerId": "anon42", "answers": {"data": {"good_ep": [false, false, true, true, true, true, true, true, true, true, true, true, true, true, true, true, true, true, true, true, true, true, true, true, true, true, true, true, true, true, true, true, true, true, true, true, true, true, true, true, true, true, true, true, true, true, true, true, true, true], "window_width": [1156, 1169, 1169, 1169, 1169, 1169, 1169, 1169, 1169, 1169, 1169, 1169, 1169, 1169, 1169, 1169, 1169, 1169, 1169, 1169, 1169, 1169, 1169, 1169, 1169, 1169, 1169, 1169, 1169, 1169, 1169, 1169, 1169, 1169, 1169, 1169, 1169, 1169, 1169, 1169, 1169, 1169, 1169, 1169, 1169, 1169, 1169, 1169, 1169, 1169], "expt_gen": ["it was fun"], "education": ["4year"], "ratings": [["5"], ["7"], ["1"], ["1"], ["1"], ["1"], ["7"], ["7"], ["7"], ["1"], ["1"], ["1"], ["7"], ["7"], ["7"], ["7"], ["1"], ["1"], ["7"], ["7"], ["7"], ["7"], ["1"], ["1", "2"], ["1"], ["7"], ["7"], ["7"], ["7"], ["1"], ["7"], ["7"], ["1"], ["1"], ["1"], ["7"], ["1"], ["7"], ["7"], ["7"], ["1"], ["7"], ["7"], ["1"], ["1", "7"], ["1", "7"], ["1"], ["1"], ["1"], ["7"]], "non_consecutive": [false, false, false, false, false, false, false, false, false, false, false, false, false, false, false, false, false, false, false, false, false, false, false, false, false, false, false, false, false, false, false, false, false, false, false, false, false, false, false, false, false, false, false, false, true, true, false, false, false, false], "elapsed_first_click_ms": [3116, 3387, 1253, 2084, 1097, 716, 896, 214, 1121, 1165, 249, 565, 453, 819, 258, 679, 627, 619, 1091, 1042, 169, 684, 529, 318, 1001, 694, 1093, 1109, 334, 643, 411, 632, 919, 827, 658, 666, 1044, 1563, 1794, 521, 1435, 1142, 1034, 2783, 903, 155, 2796, 1110, 959, 212], "adj": ["pretty", "ugly", "small", "big", "small", "small", "small", "small", "big", "small", "big", "big", "small", "big", "big", "big", "small", "big", "small", "small", "big", "small", "big", "big", "small", "big", "big", "small", "big", "big", "big", "small", "small", "big", "big", "small", "big", "small", "small", "big", "big", "big", "small", "big", "small", "small", "small", "small", "small", "big"], "num_errors": [], "dpi_width": [0, 0, 0, 0, 0, 0, 0, 0, 0, 0, 0, 0, 0, 0, 0, 0, 0, 0, 0, 0, 0, 0, 0, 0, 0, 0, 0, 0, 0, 0, 0, 0, 0, 0, 0, 0, 0, 0, 0, 0, 0, 0, 0, 0, 0, 0, 0, 0, 0, 0], "window_height": [950, 950, 950, 950, 950, 950, 950, 950, 950, 950, 950, 950, 950, 950, 950, 950, 950, 950, 950, 950, 950, 950, 950, 950, 950, 950, 950, 950, 950, 950, 950, 950, 950, 950, 950, 950, 950, 950, 950, 950, 950, 950, 950, 950, 950, 950, 950, 950, 950, 950], "screen_size": ["16"], "none_checked": [false, false, false, false, false, false, false, false, false, false, false, false, false, false, false, false, false, false, false, false, false, false, false, false, false, false, false, false, false, false, false, false, false, false, false, false, false, false, false, false, false, false, false, false, false, false, false, false, false, false], "elapsed_ms": [4000, 4121, 1988, 2621, 1948, 1448, 1664, 915, 1742, 1988, 1063, 1269, 1125, 1611, 883, 1287, 1242, 1243, 1699, 1771, 753, 1366, 1162, 1305, 1674, 1263, 1950, 1861, 1015, 1493, 1051, 1273, 1560, 1452, 2613, 1404, 1702, 2492, 2515, 1162, 2300, 1751, 1915, 3621, 3224, 3733, 3509, 1791, 1600, 758], "verb": ["are", "are", "are", "are", "are", "are", "are", "are", "are", "are", "are", "are", "are", "are", "are", "are", "are", "are", "are", "are", "are", "are", "are", "are", "are", "are", "are", "are", "are", "are", "are", "are", "are", "are", "are", "are", "are", "are", "are", "are", "are", "are", "are", "are", "are", "are", "are", "are", "are", "are"], "is_endpoint": [false, true, true, true, true, true, true, true, true, true, true, true, true, true, true, true, true, true, true, true, true, true, true, true, true, true, true, true, true, true, true, true, true, true, true, true, true, true, true, true, true, true, true, true, true, true, true, true, true, true], "lang": ["english"], "endpoint": ["na", 7, 1, 1, 1, 1, 7, 7, 7, 1, 1, 1, 7, 7, 7, 7, 1, 1, 7, 7, 7, 7, 1, 1, 1, 7, 7, 7, 7, 1, 7, 7, 1, 1, 1, 7, 1, 7, 7, 7, 1, 7, 7, 1, 1, 1, 1, 1, 1, 7], "noun": ["pretty", "car", "bean", "hazelnut", "ant", "hazelnut", "ladybug", "hazelnut", "earring", "ladybug", "blueberry", "fly", "bean", "candy", "ant", "hazelnut", "candy", "seed", "blueberry", "pill", "bean", "ant", "pill", "candy", "tack", "ladybug", "tack", "candy", "pill", "tack", "blueberry", "seed", "blueberry", "earring", "ladybug", "pin", "ant", "tack", "earring", "fly", "pin", "seed", "fly", "bean", "pin", "fly", "pill", "seed", "earring", "pin"], "gender": ["male"], "age": ["30-39"], "dpi_height": [0, 0, 0, 0, 0, 0, 0, 0, 0, 0, 0, 0, 0, 0, 0, 0, 0, 0, 0, 0, 0, 0, 0, 0, 0, 0, 0, 0, 0, 0, 0, 0, 0, 0, 0, 0, 0, 0, 0, 0, 0, 0, 0, 0, 0, 0, 0, 0, 0, 0], "expt_aim": ["human perception of sizes"], "prototype_status": ["na", "na", "na", "na", "na", "na", "na", "na", "na", "na", "na", "na", "na", "na", "na", "na", "na", "na", "na", "na", "na", "na", "na", "na", "na", "na", "na", "na", "na", "na", "na", "na", "na", "na", "na", "na", "na", "na", "na", "na", "na", "na", "na", "na", "na", "na", "na", "na", "na", "na"], "race": ["white"], "user_agent": ["Mozilla/5.0 (Windows NT 6.1; Win64; x64) AppleWebKit/537.36 (KHTML, like Gecko) Chrome/59.0.3071.115 Safari/537.36"], "num_checked": [1, 1, 1, 1, 1, 1, 1, 1, 1, 1, 1, 1, 1, 1, 1, 1, 1, 1, 1, 1, 1, 1, 1, 2, 1, 1, 1, 1, 1, 1, 1, 1, 1, 1, 1, 1, 1, 1, 1, 1, 1, 1, 1, 1, 2, 2, 1, 1, 1, 1], "dir": ["asc", "desc", "asc", "desc", "asc", "asc", "desc", "desc", "asc", "asc", "desc", "desc", "desc", "asc", "asc", "asc", "asc", "desc", "desc", "desc", "asc", "desc", "desc", "desc", "asc", "asc", "asc", "desc", "asc", "desc", "asc", "desc", "asc", "desc", "desc", "desc", "desc", "desc", "desc", "asc", "desc", "asc", "desc", "desc", "asc", "asc", "asc", "asc", "asc", "asc"]}}, "AcceptTime": "2017-08-04T16:15:46Z", "HITId": "3Z8UJEJOCYCT8VYBR1YY4JE1JHE93D", "Assignment": "", "AssignmentStatus": "Approved", "SubmitTime": "2017-08-04T18:10:17Z"}